kervi/plugin/ui/web
