Metadata-Version: 1.1
Name: kervi-ui
Version: 0.20.22
Summary: UI plugin for the kervi framework. It is included as dependency when kervi in installed.
Home-page: https://github.com/kervi/kervi-ui
Author: Tim Wentzlau
Author-email: tim.wentzlau@gmail.com
License: UNKNOWN
Download-URL: https://github.com/wentzlau/kervi-ui/archive/v1.0-alpha.tar.gz
Keywords: ui,robotic,automation
Platform: UNKNOWN
